{
  "results": [
    {
      "userFullName": "Ibrahim Dickens",
      "id": "9m-W-uI5fQUF",
      "uuid": "f4a10fbf-d12e-4a6d-b888-d86989b66687",
      "userId": "t45AiwidW",
      "likeId": "heOJ8kL74llw",
      "transactionId": "PPrW38YZtQD",
      "isRead": false,
      "createdAt": "2019-10-15T13:21:49.772Z",
      "modifiedAt": "2020-05-21T20:08:05.787Z"
    },
    {
      "userFullName": "Kaylin Homenick",
      "id": "tk8jNBQURvQz",
      "uuid": "c4ece032-38e3-47e9-8284-fbfa6d96ef9a",
      "userId": "t45AiwidW",
      "transactionId": "xAsSYDsiEGSj",
      "status": "received",
      "isRead": false,
      "createdAt": "2019-11-12T12:51:00.239Z",
      "modifiedAt": "2020-05-21T18:26:16.366Z"
    },
    {
      "userFullName": "Kaylin Homenick",
      "id": "95qRwfJnSORQ",
      "uuid": "0b5a0f25-c56b-4434-ba4d-21f133d8964f",
      "userId": "t45AiwidW",
      "transactionId": "xAsSYDsiEGSj",
      "status": "requested",
      "isRead": false,
      "createdAt": "2019-09-20T22:27:10.721Z",
      "modifiedAt": "2020-05-21T14:55:58.008Z"
    },
    {
      "userFullName": "Edgar Johns",
      "id": "Fq8xLCRtpWhT",
      "uuid": "0e2dc23a-1d85-49e5-98fb-93f9e8f961bb",
      "userId": "t45AiwidW",
      "transactionId": "76Vs0Fye9Mwt",
      "status": "received",
      "isRead": false,
      "createdAt": "2019-11-14T17:00:33.637Z",
      "modifiedAt": "2020-05-21T12:51:07.700Z"
    },
    {
      "userFullName": "Edgar Johns",
      "id": "88Nrddj3XCir",
      "uuid": "7b1697cf-4240-4eed-bc19-e60f60268b31",
      "userId": "t45AiwidW",
      "commentId": "K3HLpKcGKDiP",
      "transactionId": "lPUBZKlc4MLR",
      "isRead": false,
      "createdAt": "2019-06-20T06:13:18.420Z",
      "modifiedAt": "2020-05-21T11:22:54.822Z"
    },
    {
      "userFullName": "Edgar Johns",
      "id": "Bf5th29A1FHa",
      "uuid": "f9a7bdb3-7c32-44bf-8ce6-af31ebffd7b3",
      "userId": "t45AiwidW",
      "transactionId": "76Vs0Fye9Mwt",
      "status": "requested",
      "isRead": false,
      "createdAt": "2020-03-08T01:11:42.032Z",
      "modifiedAt": "2020-05-21T09:41:32.115Z"
    },
    {
      "userFullName": "Edgar Johns",
      "id": "kpQnRR8__imz",
      "uuid": "28e9c413-eb1c-488b-9a37-0755fd35cd15",
      "userId": "t45AiwidW",
      "transactionId": "b0mCj0O2EKHN",
      "status": "received",
      "isRead": false,
      "createdAt": "2020-01-27T17:56:05.262Z",
      "modifiedAt": "2020-05-21T09:41:18.687Z"
    },
    {
      "userFullName": "Edgar Johns",
      "id": "ojTwLrF1tDvQ",
      "uuid": "792ea312-b91f-406b-8929-77f83cdd6094",
      "userId": "t45AiwidW",
      "transactionId": "b0mCj0O2EKHN",
      "status": "requested",
      "isRead": false,
      "createdAt": "2019-11-25T00:43:47.170Z",
      "modifiedAt": "2020-05-21T02:47:36.259Z"
    },
    {
      "userFullName": "Ibrahim Dickens",
      "id": "9m-W-uI5fQUF",
      "uuid": "f4a10fbf-d12e-4a6d-b888-d86989b66687",
      "userId": "t45AiwidW",
      "likeId": "heOJ8kL74llw",
      "transactionId": "PPrW38YZtQD",
      "isRead": false,
      "createdAt": "2019-10-15T13:21:49.772Z",
      "modifiedAt": "2020-05-21T20:08:05.787Z"
    },
    {
      "userFullName": "Kaylin Homenick",
      "id": "tk8jNBQURvQz",
      "uuid": "c4ece032-38e3-47e9-8284-fbfa6d96ef9a",
      "userId": "t45AiwidW",
      "transactionId": "xAsSYDsiEGSj",
      "status": "received",
      "isRead": false,
      "createdAt": "2019-11-12T12:51:00.239Z",
      "modifiedAt": "2020-05-21T18:26:16.366Z"
    },
    {
      "userFullName": "Kaylin Homenick",
      "id": "95qRwfJnSORQ",
      "uuid": "0b5a0f25-c56b-4434-ba4d-21f133d8964f",
      "userId": "t45AiwidW",
      "transactionId": "xAsSYDsiEGSj",
      "status": "requested",
      "isRead": false,
      "createdAt": "2019-09-20T22:27:10.721Z",
      "modifiedAt": "2020-05-21T14:55:58.008Z"
    },
    {
      "userFullName": "Edgar Johns",
      "id": "Fq8xLCRtpWhT",
      "uuid": "0e2dc23a-1d85-49e5-98fb-93f9e8f961bb",
      "userId": "t45AiwidW",
      "transactionId": "76Vs0Fye9Mwt",
      "status": "received",
      "isRead": false,
      "createdAt": "2019-11-14T17:00:33.637Z",
      "modifiedAt": "2020-05-21T12:51:07.700Z"
    },
    {
      "userFullName": "Edgar Johns",
      "id": "88Nrddj3XCir",
      "uuid": "7b1697cf-4240-4eed-bc19-e60f60268b31",
      "userId": "t45AiwidW",
      "commentId": "K3HLpKcGKDiP",
      "transactionId": "lPUBZKlc4MLR",
      "isRead": false,
      "createdAt": "2019-06-20T06:13:18.420Z",
      "modifiedAt": "2020-05-21T11:22:54.822Z"
    },
    {
      "userFullName": "Edgar Johns",
      "id": "Bf5th29A1FHa",
      "uuid": "f9a7bdb3-7c32-44bf-8ce6-af31ebffd7b3",
      "userId": "t45AiwidW",
      "transactionId": "76Vs0Fye9Mwt",
      "status": "requested",
      "isRead": false,
      "createdAt": "2020-03-08T01:11:42.032Z",
      "modifiedAt": "2020-05-21T09:41:32.115Z"
    },
    {
      "userFullName": "Edgar Johns",
      "id": "kpQnRR8__imz",
      "uuid": "28e9c413-eb1c-488b-9a37-0755fd35cd15",
      "userId": "t45AiwidW",
      "transactionId": "b0mCj0O2EKHN",
      "status": "received",
      "isRead": false,
      "createdAt": "2020-01-27T17:56:05.262Z",
      "modifiedAt": "2020-05-21T09:41:18.687Z"
    },
    {
      "userFullName": "Edgar Johns",
      "id": "ojTwLrF1tDvQ",
      "uuid": "792ea312-b91f-406b-8929-77f83cdd6094",
      "userId": "t45AiwidW",
      "transactionId": "b0mCj0O2EKHN",
      "status": "requested",
      "isRead": false,
      "createdAt": "2019-11-25T00:43:47.170Z",
      "modifiedAt": "2020-05-21T02:47:36.259Z"
    }    ,
    {
      "userFullName": "Ibrahim Dickens",
      "id": "9m-W-uI5fQUF",
      "uuid": "f4a10fbf-d12e-4a6d-b888-d86989b66687",
      "userId": "t45AiwidW",
      "likeId": "heOJ8kL74llw",
      "transactionId": "PPrW38YZtQD",
      "isRead": false,
      "createdAt": "2019-10-15T13:21:49.772Z",
      "modifiedAt": "2020-05-21T20:08:05.787Z"
    },
    {
      "userFullName": "Kaylin Homenick",
      "id": "tk8jNBQURvQz",
      "uuid": "c4ece032-38e3-47e9-8284-fbfa6d96ef9a",
      "userId": "t45AiwidW",
      "transactionId": "xAsSYDsiEGSj",
      "status": "received",
      "isRead": false,
      "createdAt": "2019-11-12T12:51:00.239Z",
      "modifiedAt": "2020-05-21T18:26:16.366Z"
    },
    {
      "userFullName": "Kaylin Homenick",
      "id": "95qRwfJnSORQ",
      "uuid": "0b5a0f25-c56b-4434-ba4d-21f133d8964f",
      "userId": "t45AiwidW",
      "transactionId": "xAsSYDsiEGSj",
      "status": "requested",
      "isRead": false,
      "createdAt": "2019-09-20T22:27:10.721Z",
      "modifiedAt": "2020-05-21T14:55:58.008Z"
    },
    {
      "userFullName": "Edgar Johns",
      "id": "Fq8xLCRtpWhT",
      "uuid": "0e2dc23a-1d85-49e5-98fb-93f9e8f961bb",
      "userId": "t45AiwidW",
      "transactionId": "76Vs0Fye9Mwt",
      "status": "received",
      "isRead": false,
      "createdAt": "2019-11-14T17:00:33.637Z",
      "modifiedAt": "2020-05-21T12:51:07.700Z"
    },
    {
      "userFullName": "Edgar Johns",
      "id": "88Nrddj3XCir",
      "uuid": "7b1697cf-4240-4eed-bc19-e60f60268b31",
      "userId": "t45AiwidW",
      "commentId": "K3HLpKcGKDiP",
      "transactionId": "lPUBZKlc4MLR",
      "isRead": false,
      "createdAt": "2019-06-20T06:13:18.420Z",
      "modifiedAt": "2020-05-21T11:22:54.822Z"
    },
    {
      "userFullName": "Edgar Johns",
      "id": "Bf5th29A1FHa",
      "uuid": "f9a7bdb3-7c32-44bf-8ce6-af31ebffd7b3",
      "userId": "t45AiwidW",
      "transactionId": "76Vs0Fye9Mwt",
      "status": "requested",
      "isRead": false,
      "createdAt": "2020-03-08T01:11:42.032Z",
      "modifiedAt": "2020-05-21T09:41:32.115Z"
    },
    {
      "userFullName": "Edgar Johns",
      "id": "kpQnRR8__imz",
      "uuid": "28e9c413-eb1c-488b-9a37-0755fd35cd15",
      "userId": "t45AiwidW",
      "transactionId": "b0mCj0O2EKHN",
      "status": "received",
      "isRead": false,
      "createdAt": "2020-01-27T17:56:05.262Z",
      "modifiedAt": "2020-05-21T09:41:18.687Z"
    },
    {
      "userFullName": "Edgar Johns",
      "id": "ojTwLrF1tDvQ",
      "uuid": "792ea312-b91f-406b-8929-77f83cdd6094",
      "userId": "t45AiwidW",
      "transactionId": "b0mCj0O2EKHN",
      "status": "requested",
      "isRead": false,
      "createdAt": "2019-11-25T00:43:47.170Z",
      "modifiedAt": "2020-05-21T02:47:36.259Z"
    },
    {
      "userFullName": "Ibrahim Dickens",
      "id": "9m-W-uI5fQUF",
      "uuid": "f4a10fbf-d12e-4a6d-b888-d86989b66687",
      "userId": "t45AiwidW",
      "likeId": "heOJ8kL74llw",
      "transactionId": "PPrW38YZtQD",
      "isRead": false,
      "createdAt": "2019-10-15T13:21:49.772Z",
      "modifiedAt": "2020-05-21T20:08:05.787Z"
    },
    {
      "userFullName": "Kaylin Homenick",
      "id": "tk8jNBQURvQz",
      "uuid": "c4ece032-38e3-47e9-8284-fbfa6d96ef9a",
      "userId": "t45AiwidW",
      "transactionId": "xAsSYDsiEGSj",
      "status": "received",
      "isRead": false,
      "createdAt": "2019-11-12T12:51:00.239Z",
      "modifiedAt": "2020-05-21T18:26:16.366Z"
    },
    {
      "userFullName": "Kaylin Homenick",
      "id": "95qRwfJnSORQ",
      "uuid": "0b5a0f25-c56b-4434-ba4d-21f133d8964f",
      "userId": "t45AiwidW",
      "transactionId": "xAsSYDsiEGSj",
      "status": "requested",
      "isRead": false,
      "createdAt": "2019-09-20T22:27:10.721Z",
      "modifiedAt": "2020-05-21T14:55:58.008Z"
    },
    {
      "userFullName": "Edgar Johns",
      "id": "Fq8xLCRtpWhT",
      "uuid": "0e2dc23a-1d85-49e5-98fb-93f9e8f961bb",
      "userId": "t45AiwidW",
      "transactionId": "76Vs0Fye9Mwt",
      "status": "received",
      "isRead": false,
      "createdAt": "2019-11-14T17:00:33.637Z",
      "modifiedAt": "2020-05-21T12:51:07.700Z"
    },
    {
      "userFullName": "Edgar Johns",
      "id": "88Nrddj3XCir",
      "uuid": "7b1697cf-4240-4eed-bc19-e60f60268b31",
      "userId": "t45AiwidW",
      "commentId": "K3HLpKcGKDiP",
      "transactionId": "lPUBZKlc4MLR",
      "isRead": false,
      "createdAt": "2019-06-20T06:13:18.420Z",
      "modifiedAt": "2020-05-21T11:22:54.822Z"
    },
    {
      "userFullName": "Edgar Johns",
      "id": "Bf5th29A1FHa",
      "uuid": "f9a7bdb3-7c32-44bf-8ce6-af31ebffd7b3",
      "userId": "t45AiwidW",
      "transactionId": "76Vs0Fye9Mwt",
      "status": "requested",
      "isRead": false,
      "createdAt": "2020-03-08T01:11:42.032Z",
      "modifiedAt": "2020-05-21T09:41:32.115Z"
    },
    {
      "userFullName": "Edgar Johns",
      "id": "kpQnRR8__imz",
      "uuid": "28e9c413-eb1c-488b-9a37-0755fd35cd15",
      "userId": "t45AiwidW",
      "transactionId": "b0mCj0O2EKHN",
      "status": "received",
      "isRead": false,
      "createdAt": "2020-01-27T17:56:05.262Z",
      "modifiedAt": "2020-05-21T09:41:18.687Z"
    },
    {
      "userFullName": "Edgar Johns",
      "id": "ojTwLrF1tDvQ",
      "uuid": "792ea312-b91f-406b-8929-77f83cdd6094",
      "userId": "t45AiwidW",
      "transactionId": "b0mCj0O2EKHN",
      "status": "requested",
      "isRead": false,
      "createdAt": "2019-11-25T00:43:47.170Z",
      "modifiedAt": "2020-05-21T02:47:36.259Z"
    },
    {
      "userFullName": "Ibrahim Dickens",
      "id": "9m-W-uI5fQUF",
      "uuid": "f4a10fbf-d12e-4a6d-b888-d86989b66687",
      "userId": "t45AiwidW",
      "likeId": "heOJ8kL74llw",
      "transactionId": "PPrW38YZtQD",
      "isRead": false,
      "createdAt": "2019-10-15T13:21:49.772Z",
      "modifiedAt": "2020-05-21T20:08:05.787Z"
    },
    {
      "userFullName": "Kaylin Homenick",
      "id": "tk8jNBQURvQz",
      "uuid": "c4ece032-38e3-47e9-8284-fbfa6d96ef9a",
      "userId": "t45AiwidW",
      "transactionId": "xAsSYDsiEGSj",
      "status": "received",
      "isRead": false,
      "createdAt": "2019-11-12T12:51:00.239Z",
      "modifiedAt": "2020-05-21T18:26:16.366Z"
    },
    {
      "userFullName": "Kaylin Homenick",
      "id": "95qRwfJnSORQ",
      "uuid": "0b5a0f25-c56b-4434-ba4d-21f133d8964f",
      "userId": "t45AiwidW",
      "transactionId": "xAsSYDsiEGSj",
      "status": "requested",
      "isRead": false,
      "createdAt": "2019-09-20T22:27:10.721Z",
      "modifiedAt": "2020-05-21T14:55:58.008Z"
    },
    {
      "userFullName": "Edgar Johns",
      "id": "Fq8xLCRtpWhT",
      "uuid": "0e2dc23a-1d85-49e5-98fb-93f9e8f961bb",
      "userId": "t45AiwidW",
      "transactionId": "76Vs0Fye9Mwt",
      "status": "received",
      "isRead": false,
      "createdAt": "2019-11-14T17:00:33.637Z",
      "modifiedAt": "2020-05-21T12:51:07.700Z"
    },
    {
      "userFullName": "Edgar Johns",
      "id": "88Nrddj3XCir",
      "uuid": "7b1697cf-4240-4eed-bc19-e60f60268b31",
      "userId": "t45AiwidW",
      "commentId": "K3HLpKcGKDiP",
      "transactionId": "lPUBZKlc4MLR",
      "isRead": false,
      "createdAt": "2019-06-20T06:13:18.420Z",
      "modifiedAt": "2020-05-21T11:22:54.822Z"
    },
    {
      "userFullName": "Edgar Johns",
      "id": "Bf5th29A1FHa",
      "uuid": "f9a7bdb3-7c32-44bf-8ce6-af31ebffd7b3",
      "userId": "t45AiwidW",
      "transactionId": "76Vs0Fye9Mwt",
      "status": "requested",
      "isRead": false,
      "createdAt": "2020-03-08T01:11:42.032Z",
      "modifiedAt": "2020-05-21T09:41:32.115Z"
    },
    {
      "userFullName": "Edgar Johns",
      "id": "kpQnRR8__imz",
      "uuid": "28e9c413-eb1c-488b-9a37-0755fd35cd15",
      "userId": "t45AiwidW",
      "transactionId": "b0mCj0O2EKHN",
      "status": "received",
      "isRead": false,
      "createdAt": "2020-01-27T17:56:05.262Z",
      "modifiedAt": "2020-05-21T09:41:18.687Z"
    },
    {
      "userFullName": "Edgar Johns",
      "id": "ojTwLrF1tDvQ",
      "uuid": "792ea312-b91f-406b-8929-77f83cdd6094",
      "userId": "t45AiwidW",
      "transactionId": "b0mCj0O2EKHN",
      "status": "requested",
      "isRead": false,
      "createdAt": "2019-11-25T00:43:47.170Z",
      "modifiedAt": "2020-05-21T02:47:36.259Z"
    },
    {
      "userFullName": "Ibrahim Dickens",
      "id": "9m-W-uI5fQUF",
      "uuid": "f4a10fbf-d12e-4a6d-b888-d86989b66687",
      "userId": "t45AiwidW",
      "likeId": "heOJ8kL74llw",
      "transactionId": "PPrW38YZtQD",
      "isRead": false,
      "createdAt": "2019-10-15T13:21:49.772Z",
      "modifiedAt": "2020-05-21T20:08:05.787Z"
    },
    {
      "userFullName": "Kaylin Homenick",
      "id": "tk8jNBQURvQz",
      "uuid": "c4ece032-38e3-47e9-8284-fbfa6d96ef9a",
      "userId": "t45AiwidW",
      "transactionId": "xAsSYDsiEGSj",
      "status": "received",
      "isRead": false,
      "createdAt": "2019-11-12T12:51:00.239Z",
      "modifiedAt": "2020-05-21T18:26:16.366Z"
    },
    {
      "userFullName": "Kaylin Homenick",
      "id": "95qRwfJnSORQ",
      "uuid": "0b5a0f25-c56b-4434-ba4d-21f133d8964f",
      "userId": "t45AiwidW",
      "transactionId": "xAsSYDsiEGSj",
      "status": "requested",
      "isRead": false,
      "createdAt": "2019-09-20T22:27:10.721Z",
      "modifiedAt": "2020-05-21T14:55:58.008Z"
    },
    {
      "userFullName": "Edgar Johns",
      "id": "Fq8xLCRtpWhT",
      "uuid": "0e2dc23a-1d85-49e5-98fb-93f9e8f961bb",
      "userId": "t45AiwidW",
      "transactionId": "76Vs0Fye9Mwt",
      "status": "received",
      "isRead": false,
      "createdAt": "2019-11-14T17:00:33.637Z",
      "modifiedAt": "2020-05-21T12:51:07.700Z"
    },
    {
      "userFullName": "Edgar Johns",
      "id": "88Nrddj3XCir",
      "uuid": "7b1697cf-4240-4eed-bc19-e60f60268b31",
      "userId": "t45AiwidW",
      "commentId": "K3HLpKcGKDiP",
      "transactionId": "lPUBZKlc4MLR",
      "isRead": false,
      "createdAt": "2019-06-20T06:13:18.420Z",
      "modifiedAt": "2020-05-21T11:22:54.822Z"
    },
    {
      "userFullName": "Edgar Johns",
      "id": "Bf5th29A1FHa",
      "uuid": "f9a7bdb3-7c32-44bf-8ce6-af31ebffd7b3",
      "userId": "t45AiwidW",
      "transactionId": "76Vs0Fye9Mwt",
      "status": "requested",
      "isRead": false,
      "createdAt": "2020-03-08T01:11:42.032Z",
      "modifiedAt": "2020-05-21T09:41:32.115Z"
    },
    {
      "userFullName": "Edgar Johns",
      "id": "kpQnRR8__imz",
      "uuid": "28e9c413-eb1c-488b-9a37-0755fd35cd15",
      "userId": "t45AiwidW",
      "transactionId": "b0mCj0O2EKHN",
      "status": "received",
      "isRead": false,
      "createdAt": "2020-01-27T17:56:05.262Z",
      "modifiedAt": "2020-05-21T09:41:18.687Z"
    },
    {
      "userFullName": "Edgar Johns",
      "id": "ojTwLrF1tDvQ",
      "uuid": "792ea312-b91f-406b-8929-77f83cdd6094",
      "userId": "t45AiwidW",
      "transactionId": "b0mCj0O2EKHN",
      "status": "requested",
      "isRead": false,
      "createdAt": "2019-11-25T00:43:47.170Z",
      "modifiedAt": "2020-05-21T02:47:36.259Z"
    }    ,
    {
      "userFullName": "Ibrahim Dickens",
      "id": "9m-W-uI5fQUF",
      "uuid": "f4a10fbf-d12e-4a6d-b888-d86989b66687",
      "userId": "t45AiwidW",
      "likeId": "heOJ8kL74llw",
      "transactionId": "PPrW38YZtQD",
      "isRead": false,
      "createdAt": "2019-10-15T13:21:49.772Z",
      "modifiedAt": "2020-05-21T20:08:05.787Z"
    },
    {
      "userFullName": "Kaylin Homenick",
      "id": "tk8jNBQURvQz",
      "uuid": "c4ece032-38e3-47e9-8284-fbfa6d96ef9a",
      "userId": "t45AiwidW",
      "transactionId": "xAsSYDsiEGSj",
      "status": "received",
      "isRead": false,
      "createdAt": "2019-11-12T12:51:00.239Z",
      "modifiedAt": "2020-05-21T18:26:16.366Z"
    },
    {
      "userFullName": "Kaylin Homenick",
      "id": "95qRwfJnSORQ",
      "uuid": "0b5a0f25-c56b-4434-ba4d-21f133d8964f",
      "userId": "t45AiwidW",
      "transactionId": "xAsSYDsiEGSj",
      "status": "requested",
      "isRead": false,
      "createdAt": "2019-09-20T22:27:10.721Z",
      "modifiedAt": "2020-05-21T14:55:58.008Z"
    },
    {
      "userFullName": "Edgar Johns",
      "id": "Fq8xLCRtpWhT",
      "uuid": "0e2dc23a-1d85-49e5-98fb-93f9e8f961bb",
      "userId": "t45AiwidW",
      "transactionId": "76Vs0Fye9Mwt",
      "status": "received",
      "isRead": false,
      "createdAt": "2019-11-14T17:00:33.637Z",
      "modifiedAt": "2020-05-21T12:51:07.700Z"
    },
    {
      "userFullName": "Edgar Johns",
      "id": "88Nrddj3XCir",
      "uuid": "7b1697cf-4240-4eed-bc19-e60f60268b31",
      "userId": "t45AiwidW",
      "commentId": "K3HLpKcGKDiP",
      "transactionId": "lPUBZKlc4MLR",
      "isRead": false,
      "createdAt": "2019-06-20T06:13:18.420Z",
      "modifiedAt": "2020-05-21T11:22:54.822Z"
    },
    {
      "userFullName": "Edgar Johns",
      "id": "Bf5th29A1FHa",
      "uuid": "f9a7bdb3-7c32-44bf-8ce6-af31ebffd7b3",
      "userId": "t45AiwidW",
      "transactionId": "76Vs0Fye9Mwt",
      "status": "requested",
      "isRead": false,
      "createdAt": "2020-03-08T01:11:42.032Z",
      "modifiedAt": "2020-05-21T09:41:32.115Z"
    },
    {
      "userFullName": "Edgar Johns",
      "id": "kpQnRR8__imz",
      "uuid": "28e9c413-eb1c-488b-9a37-0755fd35cd15",
      "userId": "t45AiwidW",
      "transactionId": "b0mCj0O2EKHN",
      "status": "received",
      "isRead": false,
      "createdAt": "2020-01-27T17:56:05.262Z",
      "modifiedAt": "2020-05-21T09:41:18.687Z"
    },
    {
      "userFullName": "Edgar Johns",
      "id": "ojTwLrF1tDvQ",
      "uuid": "792ea312-b91f-406b-8929-77f83cdd6094",
      "userId": "t45AiwidW",
      "transactionId": "b0mCj0O2EKHN",
      "status": "requested",
      "isRead": false,
      "createdAt": "2019-11-25T00:43:47.170Z",
      "modifiedAt": "2020-05-21T02:47:36.259Z"
    },
    {
      "userFullName": "Ibrahim Dickens",
      "id": "9m-W-uI5fQUF",
      "uuid": "f4a10fbf-d12e-4a6d-b888-d86989b66687",
      "userId": "t45AiwidW",
      "likeId": "heOJ8kL74llw",
      "transactionId": "PPrW38YZtQD",
      "isRead": false,
      "createdAt": "2019-10-15T13:21:49.772Z",
      "modifiedAt": "2020-05-21T20:08:05.787Z"
    },
    {
      "userFullName": "Kaylin Homenick",
      "id": "tk8jNBQURvQz",
      "uuid": "c4ece032-38e3-47e9-8284-fbfa6d96ef9a",
      "userId": "t45AiwidW",
      "transactionId": "xAsSYDsiEGSj",
      "status": "received",
      "isRead": false,
      "createdAt": "2019-11-12T12:51:00.239Z",
      "modifiedAt": "2020-05-21T18:26:16.366Z"
    },
    {
      "userFullName": "Kaylin Homenick",
      "id": "95qRwfJnSORQ",
      "uuid": "0b5a0f25-c56b-4434-ba4d-21f133d8964f",
      "userId": "t45AiwidW",
      "transactionId": "xAsSYDsiEGSj",
      "status": "requested",
      "isRead": false,
      "createdAt": "2019-09-20T22:27:10.721Z",
      "modifiedAt": "2020-05-21T14:55:58.008Z"
    },
    {
      "userFullName": "Edgar Johns",
      "id": "Fq8xLCRtpWhT",
      "uuid": "0e2dc23a-1d85-49e5-98fb-93f9e8f961bb",
      "userId": "t45AiwidW",
      "transactionId": "76Vs0Fye9Mwt",
      "status": "received",
      "isRead": false,
      "createdAt": "2019-11-14T17:00:33.637Z",
      "modifiedAt": "2020-05-21T12:51:07.700Z"
    },
    {
      "userFullName": "Edgar Johns",
      "id": "88Nrddj3XCir",
      "uuid": "7b1697cf-4240-4eed-bc19-e60f60268b31",
      "userId": "t45AiwidW",
      "commentId": "K3HLpKcGKDiP",
      "transactionId": "lPUBZKlc4MLR",
      "isRead": false,
      "createdAt": "2019-06-20T06:13:18.420Z",
      "modifiedAt": "2020-05-21T11:22:54.822Z"
    },
    {
      "userFullName": "Edgar Johns",
      "id": "Bf5th29A1FHa",
      "uuid": "f9a7bdb3-7c32-44bf-8ce6-af31ebffd7b3",
      "userId": "t45AiwidW",
      "transactionId": "76Vs0Fye9Mwt",
      "status": "requested",
      "isRead": false,
      "createdAt": "2020-03-08T01:11:42.032Z",
      "modifiedAt": "2020-05-21T09:41:32.115Z"
    },
    {
      "userFullName": "Edgar Johns",
      "id": "kpQnRR8__imz",
      "uuid": "28e9c413-eb1c-488b-9a37-0755fd35cd15",
      "userId": "t45AiwidW",
      "transactionId": "b0mCj0O2EKHN",
      "status": "received",
      "isRead": false,
      "createdAt": "2020-01-27T17:56:05.262Z",
      "modifiedAt": "2020-05-21T09:41:18.687Z"
    },
    {
      "userFullName": "Edgar Johns",
      "id": "ojTwLrF1tDvQ",
      "uuid": "792ea312-b91f-406b-8929-77f83cdd6094",
      "userId": "t45AiwidW",
      "transactionId": "b0mCj0O2EKHN",
      "status": "requested",
      "isRead": false,
      "createdAt": "2019-11-25T00:43:47.170Z",
      "modifiedAt": "2020-05-21T02:47:36.259Z"
    },
    {
      "userFullName": "Ibrahim Dickens",
      "id": "9m-W-uI5fQUF",
      "uuid": "f4a10fbf-d12e-4a6d-b888-d86989b66687",
      "userId": "t45AiwidW",
      "likeId": "heOJ8kL74llw",
      "transactionId": "PPrW38YZtQD",
      "isRead": false,
      "createdAt": "2019-10-15T13:21:49.772Z",
      "modifiedAt": "2020-05-21T20:08:05.787Z"
    },
    {
      "userFullName": "Kaylin Homenick",
      "id": "tk8jNBQURvQz",
      "uuid": "c4ece032-38e3-47e9-8284-fbfa6d96ef9a",
      "userId": "t45AiwidW",
      "transactionId": "xAsSYDsiEGSj",
      "status": "received",
      "isRead": false,
      "createdAt": "2019-11-12T12:51:00.239Z",
      "modifiedAt": "2020-05-21T18:26:16.366Z"
    },
    {
      "userFullName": "Kaylin Homenick",
      "id": "95qRwfJnSORQ",
      "uuid": "0b5a0f25-c56b-4434-ba4d-21f133d8964f",
      "userId": "t45AiwidW",
      "transactionId": "xAsSYDsiEGSj",
      "status": "requested",
      "isRead": false,
      "createdAt": "2019-09-20T22:27:10.721Z",
      "modifiedAt": "2020-05-21T14:55:58.008Z"
    },
    {
      "userFullName": "Edgar Johns",
      "id": "Fq8xLCRtpWhT",
      "uuid": "0e2dc23a-1d85-49e5-98fb-93f9e8f961bb",
      "userId": "t45AiwidW",
      "transactionId": "76Vs0Fye9Mwt",
      "status": "received",
      "isRead": false,
      "createdAt": "2019-11-14T17:00:33.637Z",
      "modifiedAt": "2020-05-21T12:51:07.700Z"
    },
    {
      "userFullName": "Edgar Johns",
      "id": "88Nrddj3XCir",
      "uuid": "7b1697cf-4240-4eed-bc19-e60f60268b31",
      "userId": "t45AiwidW",
      "commentId": "K3HLpKcGKDiP",
      "transactionId": "lPUBZKlc4MLR",
      "isRead": false,
      "createdAt": "2019-06-20T06:13:18.420Z",
      "modifiedAt": "2020-05-21T11:22:54.822Z"
    },
    {
      "userFullName": "Edgar Johns",
      "id": "Bf5th29A1FHa",
      "uuid": "f9a7bdb3-7c32-44bf-8ce6-af31ebffd7b3",
      "userId": "t45AiwidW",
      "transactionId": "76Vs0Fye9Mwt",
      "status": "requested",
      "isRead": false,
      "createdAt": "2020-03-08T01:11:42.032Z",
      "modifiedAt": "2020-05-21T09:41:32.115Z"
    },
    {
      "userFullName": "Edgar Johns",
      "id": "kpQnRR8__imz",
      "uuid": "28e9c413-eb1c-488b-9a37-0755fd35cd15",
      "userId": "t45AiwidW",
      "transactionId": "b0mCj0O2EKHN",
      "status": "received",
      "isRead": false,
      "createdAt": "2020-01-27T17:56:05.262Z",
      "modifiedAt": "2020-05-21T09:41:18.687Z"
    },
    {
      "userFullName": "Edgar Johns",
      "id": "ojTwLrF1tDvQ",
      "uuid": "792ea312-b91f-406b-8929-77f83cdd6094",
      "userId": "t45AiwidW",
      "transactionId": "b0mCj0O2EKHN",
      "status": "requested",
      "isRead": false,
      "createdAt": "2019-11-25T00:43:47.170Z",
      "modifiedAt": "2020-05-21T02:47:36.259Z"
    },
    {
      "userFullName": "Ibrahim Dickens",
      "id": "9m-W-uI5fQUF",
      "uuid": "f4a10fbf-d12e-4a6d-b888-d86989b66687",
      "userId": "t45AiwidW",
      "likeId": "heOJ8kL74llw",
      "transactionId": "PPrW38YZtQD",
      "isRead": false,
      "createdAt": "2019-10-15T13:21:49.772Z",
      "modifiedAt": "2020-05-21T20:08:05.787Z"
    },
    {
      "userFullName": "Kaylin Homenick",
      "id": "tk8jNBQURvQz",
      "uuid": "c4ece032-38e3-47e9-8284-fbfa6d96ef9a",
      "userId": "t45AiwidW",
      "transactionId": "xAsSYDsiEGSj",
      "status": "received",
      "isRead": false,
      "createdAt": "2019-11-12T12:51:00.239Z",
      "modifiedAt": "2020-05-21T18:26:16.366Z"
    },
    {
      "userFullName": "Kaylin Homenick",
      "id": "95qRwfJnSORQ",
      "uuid": "0b5a0f25-c56b-4434-ba4d-21f133d8964f",
      "userId": "t45AiwidW",
      "transactionId": "xAsSYDsiEGSj",
      "status": "requested",
      "isRead": false,
      "createdAt": "2019-09-20T22:27:10.721Z",
      "modifiedAt": "2020-05-21T14:55:58.008Z"
    },
    {
      "userFullName": "Edgar Johns",
      "id": "Fq8xLCRtpWhT",
      "uuid": "0e2dc23a-1d85-49e5-98fb-93f9e8f961bb",
      "userId": "t45AiwidW",
      "transactionId": "76Vs0Fye9Mwt",
      "status": "received",
      "isRead": false,
      "createdAt": "2019-11-14T17:00:33.637Z",
      "modifiedAt": "2020-05-21T12:51:07.700Z"
    },
    {
      "userFullName": "Edgar Johns",
      "id": "88Nrddj3XCir",
      "uuid": "7b1697cf-4240-4eed-bc19-e60f60268b31",
      "userId": "t45AiwidW",
      "commentId": "K3HLpKcGKDiP",
      "transactionId": "lPUBZKlc4MLR",
      "isRead": false,
      "createdAt": "2019-06-20T06:13:18.420Z",
      "modifiedAt": "2020-05-21T11:22:54.822Z"
    },
    {
      "userFullName": "Edgar Johns",
      "id": "Bf5th29A1FHa",
      "uuid": "f9a7bdb3-7c32-44bf-8ce6-af31ebffd7b3",
      "userId": "t45AiwidW",
      "transactionId": "76Vs0Fye9Mwt",
      "status": "requested",
      "isRead": false,
      "createdAt": "2020-03-08T01:11:42.032Z",
      "modifiedAt": "2020-05-21T09:41:32.115Z"
    },
    {
      "userFullName": "Edgar Johns",
      "id": "kpQnRR8__imz",
      "uuid": "28e9c413-eb1c-488b-9a37-0755fd35cd15",
      "userId": "t45AiwidW",
      "transactionId": "b0mCj0O2EKHN",
      "status": "received",
      "isRead": false,
      "createdAt": "2020-01-27T17:56:05.262Z",
      "modifiedAt": "2020-05-21T09:41:18.687Z"
    },
    {
      "userFullName": "Edgar Johns",
      "id": "ojTwLrF1tDvQ",
      "uuid": "792ea312-b91f-406b-8929-77f83cdd6094",
      "userId": "t45AiwidW",
      "transactionId": "b0mCj0O2EKHN",
      "status": "requested",
      "isRead": false,
      "createdAt": "2019-11-25T00:43:47.170Z",
      "modifiedAt": "2020-05-21T02:47:36.259Z"
    }    ,
    {
      "userFullName": "Ibrahim Dickens",
      "id": "9m-W-uI5fQUF",
      "uuid": "f4a10fbf-d12e-4a6d-b888-d86989b66687",
      "userId": "t45AiwidW",
      "likeId": "heOJ8kL74llw",
      "transactionId": "PPrW38YZtQD",
      "isRead": false,
      "createdAt": "2019-10-15T13:21:49.772Z",
      "modifiedAt": "2020-05-21T20:08:05.787Z"
    },
    {
      "userFullName": "Kaylin Homenick",
      "id": "tk8jNBQURvQz",
      "uuid": "c4ece032-38e3-47e9-8284-fbfa6d96ef9a",
      "userId": "t45AiwidW",
      "transactionId": "xAsSYDsiEGSj",
      "status": "received",
      "isRead": false,
      "createdAt": "2019-11-12T12:51:00.239Z",
      "modifiedAt": "2020-05-21T18:26:16.366Z"
    },
    {
      "userFullName": "Kaylin Homenick",
      "id": "95qRwfJnSORQ",
      "uuid": "0b5a0f25-c56b-4434-ba4d-21f133d8964f",
      "userId": "t45AiwidW",
      "transactionId": "xAsSYDsiEGSj",
      "status": "requested",
      "isRead": false,
      "createdAt": "2019-09-20T22:27:10.721Z",
      "modifiedAt": "2020-05-21T14:55:58.008Z"
    },
    {
      "userFullName": "Edgar Johns",
      "id": "Fq8xLCRtpWhT",
      "uuid": "0e2dc23a-1d85-49e5-98fb-93f9e8f961bb",
      "userId": "t45AiwidW",
      "transactionId": "76Vs0Fye9Mwt",
      "status": "received",
      "isRead": false,
      "createdAt": "2019-11-14T17:00:33.637Z",
      "modifiedAt": "2020-05-21T12:51:07.700Z"
    },
    {
      "userFullName": "Edgar Johns",
      "id": "88Nrddj3XCir",
      "uuid": "7b1697cf-4240-4eed-bc19-e60f60268b31",
      "userId": "t45AiwidW",
      "commentId": "K3HLpKcGKDiP",
      "transactionId": "lPUBZKlc4MLR",
      "isRead": false,
      "createdAt": "2019-06-20T06:13:18.420Z",
      "modifiedAt": "2020-05-21T11:22:54.822Z"
    },
    {
      "userFullName": "Edgar Johns",
      "id": "Bf5th29A1FHa",
      "uuid": "f9a7bdb3-7c32-44bf-8ce6-af31ebffd7b3",
      "userId": "t45AiwidW",
      "transactionId": "76Vs0Fye9Mwt",
      "status": "requested",
      "isRead": false,
      "createdAt": "2020-03-08T01:11:42.032Z",
      "modifiedAt": "2020-05-21T09:41:32.115Z"
    },
    {
      "userFullName": "Edgar Johns",
      "id": "kpQnRR8__imz",
      "uuid": "28e9c413-eb1c-488b-9a37-0755fd35cd15",
      "userId": "t45AiwidW",
      "transactionId": "b0mCj0O2EKHN",
      "status": "received",
      "isRead": false,
      "createdAt": "2020-01-27T17:56:05.262Z",
      "modifiedAt": "2020-05-21T09:41:18.687Z"
    },
    {
      "userFullName": "Edgar Johns",
      "id": "ojTwLrF1tDvQ",
      "uuid": "792ea312-b91f-406b-8929-77f83cdd6094",
      "userId": "t45AiwidW",
      "transactionId": "b0mCj0O2EKHN",
      "status": "requested",
      "isRead": false,
      "createdAt": "2019-11-25T00:43:47.170Z",
      "modifiedAt": "2020-05-21T02:47:36.259Z"
    },
    {
      "userFullName": "Ibrahim Dickens",
      "id": "9m-W-uI5fQUF",
      "uuid": "f4a10fbf-d12e-4a6d-b888-d86989b66687",
      "userId": "t45AiwidW",
      "likeId": "heOJ8kL74llw",
      "transactionId": "PPrW38YZtQD",
      "isRead": false,
      "createdAt": "2019-10-15T13:21:49.772Z",
      "modifiedAt": "2020-05-21T20:08:05.787Z"
    },
    {
      "userFullName": "Kaylin Homenick",
      "id": "tk8jNBQURvQz",
      "uuid": "c4ece032-38e3-47e9-8284-fbfa6d96ef9a",
      "userId": "t45AiwidW",
      "transactionId": "xAsSYDsiEGSj",
      "status": "received",
      "isRead": false,
      "createdAt": "2019-11-12T12:51:00.239Z",
      "modifiedAt": "2020-05-21T18:26:16.366Z"
    },
    {
      "userFullName": "Kaylin Homenick",
      "id": "95qRwfJnSORQ",
      "uuid": "0b5a0f25-c56b-4434-ba4d-21f133d8964f",
      "userId": "t45AiwidW",
      "transactionId": "xAsSYDsiEGSj",
      "status": "requested",
      "isRead": false,
      "createdAt": "2019-09-20T22:27:10.721Z",
      "modifiedAt": "2020-05-21T14:55:58.008Z"
    },
    {
      "userFullName": "Edgar Johns",
      "id": "Fq8xLCRtpWhT",
      "uuid": "0e2dc23a-1d85-49e5-98fb-93f9e8f961bb",
      "userId": "t45AiwidW",
      "transactionId": "76Vs0Fye9Mwt",
      "status": "received",
      "isRead": false,
      "createdAt": "2019-11-14T17:00:33.637Z",
      "modifiedAt": "2020-05-21T12:51:07.700Z"
    },
    {
      "userFullName": "Edgar Johns",
      "id": "88Nrddj3XCir",
      "uuid": "7b1697cf-4240-4eed-bc19-e60f60268b31",
      "userId": "t45AiwidW",
      "commentId": "K3HLpKcGKDiP",
      "transactionId": "lPUBZKlc4MLR",
      "isRead": false,
      "createdAt": "2019-06-20T06:13:18.420Z",
      "modifiedAt": "2020-05-21T11:22:54.822Z"
    },
    {
      "userFullName": "Edgar Johns",
      "id": "Bf5th29A1FHa",
      "uuid": "f9a7bdb3-7c32-44bf-8ce6-af31ebffd7b3",
      "userId": "t45AiwidW",
      "transactionId": "76Vs0Fye9Mwt",
      "status": "requested",
      "isRead": false,
      "createdAt": "2020-03-08T01:11:42.032Z",
      "modifiedAt": "2020-05-21T09:41:32.115Z"
    },
    {
      "userFullName": "Edgar Johns",
      "id": "kpQnRR8__imz",
      "uuid": "28e9c413-eb1c-488b-9a37-0755fd35cd15",
      "userId": "t45AiwidW",
      "transactionId": "b0mCj0O2EKHN",
      "status": "received",
      "isRead": false,
      "createdAt": "2020-01-27T17:56:05.262Z",
      "modifiedAt": "2020-05-21T09:41:18.687Z"
    },
    {
      "userFullName": "Edgar Johns",
      "id": "ojTwLrF1tDvQ",
      "uuid": "792ea312-b91f-406b-8929-77f83cdd6094",
      "userId": "t45AiwidW",
      "transactionId": "b0mCj0O2EKHN",
      "status": "requested",
      "isRead": false,
      "createdAt": "2019-11-25T00:43:47.170Z",
      "modifiedAt": "2020-05-21T02:47:36.259Z"
    },
    {
      "userFullName": "Ibrahim Dickens",
      "id": "9m-W-uI5fQUF",
      "uuid": "f4a10fbf-d12e-4a6d-b888-d86989b66687",
      "userId": "t45AiwidW",
      "likeId": "heOJ8kL74llw",
      "transactionId": "PPrW38YZtQD",
      "isRead": false,
      "createdAt": "2019-10-15T13:21:49.772Z",
      "modifiedAt": "2020-05-21T20:08:05.787Z"
    },
    {
      "userFullName": "Kaylin Homenick",
      "id": "tk8jNBQURvQz",
      "uuid": "c4ece032-38e3-47e9-8284-fbfa6d96ef9a",
      "userId": "t45AiwidW",
      "transactionId": "xAsSYDsiEGSj",
      "status": "received",
      "isRead": false,
      "createdAt": "2019-11-12T12:51:00.239Z",
      "modifiedAt": "2020-05-21T18:26:16.366Z"
    },
    {
      "userFullName": "Kaylin Homenick",
      "id": "95qRwfJnSORQ",
      "uuid": "0b5a0f25-c56b-4434-ba4d-21f133d8964f",
      "userId": "t45AiwidW",
      "transactionId": "xAsSYDsiEGSj",
      "status": "requested",
      "isRead": false,
      "createdAt": "2019-09-20T22:27:10.721Z",
      "modifiedAt": "2020-05-21T14:55:58.008Z"
    },
    {
      "userFullName": "Edgar Johns",
      "id": "Fq8xLCRtpWhT",
      "uuid": "0e2dc23a-1d85-49e5-98fb-93f9e8f961bb",
      "userId": "t45AiwidW",
      "transactionId": "76Vs0Fye9Mwt",
      "status": "received",
      "isRead": false,
      "createdAt": "2019-11-14T17:00:33.637Z",
      "modifiedAt": "2020-05-21T12:51:07.700Z"
    },
    {
      "userFullName": "Edgar Johns",
      "id": "88Nrddj3XCir",
      "uuid": "7b1697cf-4240-4eed-bc19-e60f60268b31",
      "userId": "t45AiwidW",
      "commentId": "K3HLpKcGKDiP",
      "transactionId": "lPUBZKlc4MLR",
      "isRead": false,
      "createdAt": "2019-06-20T06:13:18.420Z",
      "modifiedAt": "2020-05-21T11:22:54.822Z"
    },
    {
      "userFullName": "Edgar Johns",
      "id": "Bf5th29A1FHa",
      "uuid": "f9a7bdb3-7c32-44bf-8ce6-af31ebffd7b3",
      "userId": "t45AiwidW",
      "transactionId": "76Vs0Fye9Mwt",
      "status": "requested",
      "isRead": false,
      "createdAt": "2020-03-08T01:11:42.032Z",
      "modifiedAt": "2020-05-21T09:41:32.115Z"
    },
    {
      "userFullName": "Edgar Johns",
      "id": "kpQnRR8__imz",
      "uuid": "28e9c413-eb1c-488b-9a37-0755fd35cd15",
      "userId": "t45AiwidW",
      "transactionId": "b0mCj0O2EKHN",
      "status": "received",
      "isRead": false,
      "createdAt": "2020-01-27T17:56:05.262Z",
      "modifiedAt": "2020-05-21T09:41:18.687Z"
    },
    {
      "userFullName": "Edgar Johns",
      "id": "ojTwLrF1tDvQ",
      "uuid": "792ea312-b91f-406b-8929-77f83cdd6094",
      "userId": "t45AiwidW",
      "transactionId": "b0mCj0O2EKHN",
      "status": "requested",
      "isRead": false,
      "createdAt": "2019-11-25T00:43:47.170Z",
      "modifiedAt": "2020-05-21T02:47:36.259Z"
    },
    {
      "userFullName": "Ibrahim Dickens",
      "id": "9m-W-uI5fQUF",
      "uuid": "f4a10fbf-d12e-4a6d-b888-d86989b66687",
      "userId": "t45AiwidW",
      "likeId": "heOJ8kL74llw",
      "transactionId": "PPrW38YZtQD",
      "isRead": false,
      "createdAt": "2019-10-15T13:21:49.772Z",
      "modifiedAt": "2020-05-21T20:08:05.787Z"
    },
    {
      "userFullName": "Kaylin Homenick",
      "id": "tk8jNBQURvQz",
      "uuid": "c4ece032-38e3-47e9-8284-fbfa6d96ef9a",
      "userId": "t45AiwidW",
      "transactionId": "xAsSYDsiEGSj",
      "status": "received",
      "isRead": false,
      "createdAt": "2019-11-12T12:51:00.239Z",
      "modifiedAt": "2020-05-21T18:26:16.366Z"
    },
    {
      "userFullName": "Kaylin Homenick",
      "id": "95qRwfJnSORQ",
      "uuid": "0b5a0f25-c56b-4434-ba4d-21f133d8964f",
      "userId": "t45AiwidW",
      "transactionId": "xAsSYDsiEGSj",
      "status": "requested",
      "isRead": false,
      "createdAt": "2019-09-20T22:27:10.721Z",
      "modifiedAt": "2020-05-21T14:55:58.008Z"
    },
    {
      "userFullName": "Edgar Johns",
      "id": "Fq8xLCRtpWhT",
      "uuid": "0e2dc23a-1d85-49e5-98fb-93f9e8f961bb",
      "userId": "t45AiwidW",
      "transactionId": "76Vs0Fye9Mwt",
      "status": "received",
      "isRead": false,
      "createdAt": "2019-11-14T17:00:33.637Z",
      "modifiedAt": "2020-05-21T12:51:07.700Z"
    },
    {
      "userFullName": "Edgar Johns",
      "id": "88Nrddj3XCir",
      "uuid": "7b1697cf-4240-4eed-bc19-e60f60268b31",
      "userId": "t45AiwidW",
      "commentId": "K3HLpKcGKDiP",
      "transactionId": "lPUBZKlc4MLR",
      "isRead": false,
      "createdAt": "2019-06-20T06:13:18.420Z",
      "modifiedAt": "2020-05-21T11:22:54.822Z"
    },
    {
      "userFullName": "Edgar Johns",
      "id": "Bf5th29A1FHa",
      "uuid": "f9a7bdb3-7c32-44bf-8ce6-af31ebffd7b3",
      "userId": "t45AiwidW",
      "transactionId": "76Vs0Fye9Mwt",
      "status": "requested",
      "isRead": false,
      "createdAt": "2020-03-08T01:11:42.032Z",
      "modifiedAt": "2020-05-21T09:41:32.115Z"
    },
    {
      "userFullName": "Edgar Johns",
      "id": "kpQnRR8__imz",
      "uuid": "28e9c413-eb1c-488b-9a37-0755fd35cd15",
      "userId": "t45AiwidW",
      "transactionId": "b0mCj0O2EKHN",
      "status": "received",
      "isRead": false,
      "createdAt": "2020-01-27T17:56:05.262Z",
      "modifiedAt": "2020-05-21T09:41:18.687Z"
    },
    {
      "userFullName": "Edgar Johns",
      "id": "ojTwLrF1tDvQ",
      "uuid": "792ea312-b91f-406b-8929-77f83cdd6094",
      "userId": "t45AiwidW",
      "transactionId": "b0mCj0O2EKHN",
      "status": "requested",
      "isRead": false,
      "createdAt": "2019-11-25T00:43:47.170Z",
      "modifiedAt": "2020-05-21T02:47:36.259Z"
    }    ,
    {
      "userFullName": "Ibrahim Dickens",
      "id": "9m-W-uI5fQUF",
      "uuid": "f4a10fbf-d12e-4a6d-b888-d86989b66687",
      "userId": "t45AiwidW",
      "likeId": "heOJ8kL74llw",
      "transactionId": "PPrW38YZtQD",
      "isRead": false,
      "createdAt": "2019-10-15T13:21:49.772Z",
      "modifiedAt": "2020-05-21T20:08:05.787Z"
    },
    {
      "userFullName": "Kaylin Homenick",
      "id": "tk8jNBQURvQz",
      "uuid": "c4ece032-38e3-47e9-8284-fbfa6d96ef9a",
      "userId": "t45AiwidW",
      "transactionId": "xAsSYDsiEGSj",
      "status": "received",
      "isRead": false,
      "createdAt": "2019-11-12T12:51:00.239Z",
      "modifiedAt": "2020-05-21T18:26:16.366Z"
    },
    {
      "userFullName": "Kaylin Homenick",
      "id": "95qRwfJnSORQ",
      "uuid": "0b5a0f25-c56b-4434-ba4d-21f133d8964f",
      "userId": "t45AiwidW",
      "transactionId": "xAsSYDsiEGSj",
      "status": "requested",
      "isRead": false,
      "createdAt": "2019-09-20T22:27:10.721Z",
      "modifiedAt": "2020-05-21T14:55:58.008Z"
    },
    {
      "userFullName": "Edgar Johns",
      "id": "Fq8xLCRtpWhT",
      "uuid": "0e2dc23a-1d85-49e5-98fb-93f9e8f961bb",
      "userId": "t45AiwidW",
      "transactionId": "76Vs0Fye9Mwt",
      "status": "received",
      "isRead": false,
      "createdAt": "2019-11-14T17:00:33.637Z",
      "modifiedAt": "2020-05-21T12:51:07.700Z"
    },
    {
      "userFullName": "Edgar Johns",
      "id": "88Nrddj3XCir",
      "uuid": "7b1697cf-4240-4eed-bc19-e60f60268b31",
      "userId": "t45AiwidW",
      "commentId": "K3HLpKcGKDiP",
      "transactionId": "lPUBZKlc4MLR",
      "isRead": false,
      "createdAt": "2019-06-20T06:13:18.420Z",
      "modifiedAt": "2020-05-21T11:22:54.822Z"
    },
    {
      "userFullName": "Edgar Johns",
      "id": "Bf5th29A1FHa",
      "uuid": "f9a7bdb3-7c32-44bf-8ce6-af31ebffd7b3",
      "userId": "t45AiwidW",
      "transactionId": "76Vs0Fye9Mwt",
      "status": "requested",
      "isRead": false,
      "createdAt": "2020-03-08T01:11:42.032Z",
      "modifiedAt": "2020-05-21T09:41:32.115Z"
    },
    {
      "userFullName": "Edgar Johns",
      "id": "kpQnRR8__imz",
      "uuid": "28e9c413-eb1c-488b-9a37-0755fd35cd15",
      "userId": "t45AiwidW",
      "transactionId": "b0mCj0O2EKHN",
      "status": "received",
      "isRead": false,
      "createdAt": "2020-01-27T17:56:05.262Z",
      "modifiedAt": "2020-05-21T09:41:18.687Z"
    },
    {
      "userFullName": "Edgar Johns",
      "id": "ojTwLrF1tDvQ",
      "uuid": "792ea312-b91f-406b-8929-77f83cdd6094",
      "userId": "t45AiwidW",
      "transactionId": "b0mCj0O2EKHN",
      "status": "requested",
      "isRead": false,
      "createdAt": "2019-11-25T00:43:47.170Z",
      "modifiedAt": "2020-05-21T02:47:36.259Z"
    },
    {
      "userFullName": "Ibrahim Dickens",
      "id": "9m-W-uI5fQUF",
      "uuid": "f4a10fbf-d12e-4a6d-b888-d86989b66687",
      "userId": "t45AiwidW",
      "likeId": "heOJ8kL74llw",
      "transactionId": "PPrW38YZtQD",
      "isRead": false,
      "createdAt": "2019-10-15T13:21:49.772Z",
      "modifiedAt": "2020-05-21T20:08:05.787Z"
    },
    {
      "userFullName": "Kaylin Homenick",
      "id": "tk8jNBQURvQz",
      "uuid": "c4ece032-38e3-47e9-8284-fbfa6d96ef9a",
      "userId": "t45AiwidW",
      "transactionId": "xAsSYDsiEGSj",
      "status": "received",
      "isRead": false,
      "createdAt": "2019-11-12T12:51:00.239Z",
      "modifiedAt": "2020-05-21T18:26:16.366Z"
    },
    {
      "userFullName": "Kaylin Homenick",
      "id": "95qRwfJnSORQ",
      "uuid": "0b5a0f25-c56b-4434-ba4d-21f133d8964f",
      "userId": "t45AiwidW",
      "transactionId": "xAsSYDsiEGSj",
      "status": "requested",
      "isRead": false,
      "createdAt": "2019-09-20T22:27:10.721Z",
      "modifiedAt": "2020-05-21T14:55:58.008Z"
    },
    {
      "userFullName": "Edgar Johns",
      "id": "Fq8xLCRtpWhT",
      "uuid": "0e2dc23a-1d85-49e5-98fb-93f9e8f961bb",
      "userId": "t45AiwidW",
      "transactionId": "76Vs0Fye9Mwt",
      "status": "received",
      "isRead": false,
      "createdAt": "2019-11-14T17:00:33.637Z",
      "modifiedAt": "2020-05-21T12:51:07.700Z"
    },
    {
      "userFullName": "Edgar Johns",
      "id": "88Nrddj3XCir",
      "uuid": "7b1697cf-4240-4eed-bc19-e60f60268b31",
      "userId": "t45AiwidW",
      "commentId": "K3HLpKcGKDiP",
      "transactionId": "lPUBZKlc4MLR",
      "isRead": false,
      "createdAt": "2019-06-20T06:13:18.420Z",
      "modifiedAt": "2020-05-21T11:22:54.822Z"
    },
    {
      "userFullName": "Edgar Johns",
      "id": "Bf5th29A1FHa",
      "uuid": "f9a7bdb3-7c32-44bf-8ce6-af31ebffd7b3",
      "userId": "t45AiwidW",
      "transactionId": "76Vs0Fye9Mwt",
      "status": "requested",
      "isRead": false,
      "createdAt": "2020-03-08T01:11:42.032Z",
      "modifiedAt": "2020-05-21T09:41:32.115Z"
    },
    {
      "userFullName": "Edgar Johns",
      "id": "kpQnRR8__imz",
      "uuid": "28e9c413-eb1c-488b-9a37-0755fd35cd15",
      "userId": "t45AiwidW",
      "transactionId": "b0mCj0O2EKHN",
      "status": "received",
      "isRead": false,
      "createdAt": "2020-01-27T17:56:05.262Z",
      "modifiedAt": "2020-05-21T09:41:18.687Z"
    },
    {
      "userFullName": "Edgar Johns",
      "id": "ojTwLrF1tDvQ",
      "uuid": "792ea312-b91f-406b-8929-77f83cdd6094",
      "userId": "t45AiwidW",
      "transactionId": "b0mCj0O2EKHN",
      "status": "requested",
      "isRead": false,
      "createdAt": "2019-11-25T00:43:47.170Z",
      "modifiedAt": "2020-05-21T02:47:36.259Z"
    }
  ]
}
